cuddly_invention/__about__.py
cuddly_invention/__init__.py
cuddly_invention/__main__.py
cuddly_invention-0.2.0.dist-info/METADATA
cuddly_invention-0.2.0.dist-info/WHEEL
cuddly_invention-0.2.0.dist-info/licenses/LICENSE
cuddly_invention-0.2.0.dist-info/RECORD
