Metadata-Version: 2.3
Name: cuddly-invention
Version: 0.2.0
Project-URL: Documentation, https://github.com/unknown/cuddly-invention#readme
Project-URL: Issues, https://github.com/unknown/cuddly-invention/issues
Project-URL: Source, https://github.com/unknown/cuddly-invention
Author-email: MtkN1 <51289448+MtkN1@users.noreply.github.com>
License-Expression: MIT
License-File: LICENSE
Classifier: Development Status :: 4 - Beta
Classifier: Programming Language :: Python
Classifier: Programming Language :: Python :: 3.8
Classifier: Programming Language :: Python :: 3.9
Classifier: Programming Language :: Python :: 3.10
Classifier: Programming Language :: Python :: 3.11
Classifier: Programming Language :: Python :: 3.12
Classifier: Programming Language :: Python :: Implementation :: CPython
Classifier: Programming Language :: Python :: Implementation :: PyPy
Requires-Python: >=3.8
